aiogram_declarative/__init__.py
aiogram_declarative/abc/__init__.py
aiogram_declarative/abc/addon.py
aiogram_declarative/src/__init__.py
aiogram_declarative/src/cb_data.py
aiogram_declarative/src/core_joint.py
aiogram_declarative/src/dialog_addon.py
aiogram_declarative/src/registry.py
aiogram_declarative/src/router.py
aiogram_declarative/src/telegram_event_observer.py
aiogram_declarative/src/utils.py
aiogram_declarative-0.1.13.dist-info/LICENSE
aiogram_declarative-0.1.13.dist-info/WHEEL
aiogram_declarative-0.1.13.dist-info/METADATA
aiogram_declarative-0.1.13.dist-info/RECORD
