Metadata-Version: 2.1
Name: aiogram-declarative
Version: 0.1.13
Summary: Another way to struct your telegram bots via Aiogram3
Home-page: https://github.com/Arustinal/aiogram_declarative
License: MIT
Author: Aleks
Requires-Python: >=3.8,<4.0
Classifier: License :: OSI Approved :: MIT License
Classifier: Programming Language :: Python :: 3
Classifier: Programming Language :: Python :: 3.10
Classifier: Programming Language :: Python :: 3.8
Classifier: Programming Language :: Python :: 3.9
Requires-Dist: aiogram (>=3.0.0b2,<4.0.0)
Requires-Dist: aiogram_dialog (>=2.0.0b2,<3.0.0)
Project-URL: Repository, https://github.com/Arustinal/aiogram_declarative
